CHANGES.rst
LICENSE
MANIFEST.in
README.rst
requirements.txt
setup.py
edt2ics/__init__.py
edt2ics/cli.py
edt2ics/dates.json
edt2ics/events.py
edt2ics/ical.py
edt2ics/scraper.py
p7edt2ics.egg-info/PKG-INFO
p7edt2ics.egg-info/SOURCES.txt
p7edt2ics.egg-info/dependency_links.txt
p7edt2ics.egg-info/entry_points.txt
p7edt2ics.egg-info/requires.txt
p7edt2ics.egg-info/top_level.txt