Metadata-Version: 1.1
Name: p7edt2ics
Version: 0.1.2-alpha2
Summary: Paris Diderot CS dep. iCalendar schedule converter
Home-page: https://github.com/bfontaine/edt2ics
Author: Baptiste Fontaine
Author-email: b@ptistefontaine.fr
License: Copyright © 2014 – Baptiste Fontaine
